django_exportapp/__init__.py
django_exportapp/apps.py
django_exportapp/helper.py
django_exportapp/utils.py
django_exportapp/management/__init__.py
django_exportapp/management/commands/__init__.py
django_exportapp/management/commands/run_exporter.py
django_exportapp-0.1.2.dist-info/LICENSE
django_exportapp-0.1.2.dist-info/METADATA
django_exportapp-0.1.2.dist-info/WHEEL
django_exportapp-0.1.2.dist-info/top_level.txt
django_exportapp-0.1.2.dist-info/RECORD
